<?xml version='1.0' encoding='utf-8'?>
<SigAbility>
  <Key>UNMATCHEDINGEN</Key>
  <Name>Непревзойденное мастерство (Unmatched Ingenuity)</Name>
  <Description>Перед боем (или даже в разгар боя, если представится такая возможность) Инженеры любят возиться со своим оборудованием. Любой Инженер, стоящий своих гидрошпангоутов, переделает подачу патронов в пулеметы, переставит датчики детонатора ракеты или переложит силовые каналы в бластерах. В сознании Инженеров нет ничего, что нельзя было бы улучшить, а использование оружия в том виде, в котором оно поступило из источников снабжения, - признак лени или недостатка мастерства. Они гордятся тем, что всегда добавляют какое-нибудь гениальное усовершенствование не только к своему оружию, но и к оружию своих товарищей по Альянсу.
  
[BR][P]Один раз за игровую сессию в качестве действия персонаж может потратить 2 очка "Судьбы" и сделать [B]Сложную ([DI][DI][DI]) проверку "Механики"[b]. В случае успеха он может добавить одно качество предмета (кроме "Breach" или "Concussive") к оружию или предмету, который он держит в руках или которым управляет. Если возможно, качество предмета имеет рейтинг 1. Персонаж может потратить [TR], чтобы добавить одно дополнительное качество к тому же предмету, и [AD], чтобы увеличить рейтинг качества предмета на 1. Это изменение длится 2 раунда или 10 минут повествовательного времени.</Description>
  <Source Page="35">Дополнение: Полная оперативность (Fully Operational)</Source>
  <Custom>DescOnly</Custom>
  <AbilityRows>
    <AbilityRow>
      <Abilities>
        <Key>UNMATCHEDINGENBASE</Key>
        <Key>UNMATCHEDINGENBASE</Key>
        <Key>UNMATCHEDINGENBASE</Key>
        <Key>UNMATCHEDINGENBASE</Key>
      </Abilities>
      <Directions>
        <Direction>
          <Down>true</Down>
        </Direction>
        <Direction>
          <Down>true</Down>
        </Direction>
        <Direction>
          <Down>true</Down>
        </Direction>
        <Direction />
      </Directions>
      <AbilitySpan>
        <Span>4</Span>
        <Span>0</Span>
        <Span>0</Span>
        <Span>0</Span>
      </AbilitySpan>
      <Costs>
        <Cost>30</Cost>
        <Cost>0</Cost>
        <Cost>0</Cost>
        <Cost>0</Cost>
      </Costs>
    </AbilityRow>
    <AbilityRow>
      <Abilities>
        <Key>UNMATCHEDINGENADDBOOST</Key>
        <Key>UNMATCHEDINGENDURATION</Key>
        <Key>UNMATCHEDINGENADDBOOST</Key>
        <Key>UNMATCHEDINGENDURATION</Key>
      </Abilities>
      <Directions>
        <Direction>
          <Up>true</Up>
          <Down>true</Down>
        </Direction>
        <Direction>
          <Up>true</Up>
        </Direction>
        <Direction>
          <Right>true</Right>
          <Up>true</Up>
          <Down>true</Down>
        </Direction>
        <Direction>
          <Left>true</Left>
        </Direction>
      </Directions>
      <AbilitySpan>
        <Span>1</Span>
        <Span>1</Span>
        <Span>1</Span>
        <Span>1</Span>
      </AbilitySpan>
      <Costs>
        <Cost>10</Cost>
        <Cost>10</Cost>
        <Cost>10</Cost>
        <Cost>10</Cost>
      </Costs>
    </AbilityRow>
    <AbilityRow>
      <Abilities>
        <Key>UNMATCHEDINGENQUALITY</Key>
        <Key>UNMATCHEDINGENDESTINY</Key>
        <Key>UNMATCHEDINGENREDUCEDIFF</Key>
        <Key>UNMATCHEDINGENQUALITY2</Key>
      </Abilities>
      <Directions>
        <Direction>
          <Up>true</Up>
        </Direction>
        <Direction>
          <Right>true</Right>
        </Direction>
        <Direction>
          <Left>true</Left>
          <Right>true</Right>
          <Up>true</Up>
        </Direction>
        <Direction>
          <Left>true</Left>
        </Direction>
      </Directions>
      <AbilitySpan>
        <Span>1</Span>
        <Span>1</Span>
        <Span>1</Span>
        <Span>1</Span>
      </AbilitySpan>
      <Costs>
        <Cost>15</Cost>
        <Cost>15</Cost>
        <Cost>15</Cost>
        <Cost>15</Cost>
      </Costs>
    </AbilityRow>
  </AbilityRows>
  <Careers>
    <Key>ENGINEER</Key>
  </Careers>
  <MatchingNodes>
    <Node>false</Node>
    <Node>true</Node>
    <Node>true</Node>
    <Node>false</Node>
  </MatchingNodes>
</SigAbility>
